inxlib/__init__.py
inxlib/app.py
inxlib/middleware.py
inxlib/response.py
inxlib-0.1.2.dist-info/METADATA
inxlib-0.1.2.dist-info/WHEEL
inxlib-0.1.2.dist-info/top_level.txt
inxlib-0.1.2.dist-info/RECORD
