Metadata-Version: 2.1
Name: inxlib
Version: 0.1.2
Summary: Python Web Framework
Home-page: https://github.com/me/myproject
Author: Numonjon Ibrokhimov
Author-email: nexusinx00@gmail.com
License: MIT
Platform: UNKNOWN
Classifier: License :: OSI Approved :: MIT License
Classifier: Programming Language :: Python
Classifier: Programming Language :: Python :: 3
Classifier: Programming Language :: Python :: 3.6
Classifier: Programming Language :: Python :: Implementation :: CPython
Classifier: Programming Language :: Python :: Implementation :: PyPy
Requires-Python: >=3.10.12
Requires-Dist: Jinja2==3.1.6
Requires-Dist: WebOb==1.8.9
Requires-Dist: parse==1.20.2
Requires-Dist: requests-wsgi-adapter==0.4.1
Requires-Dist: requests==2.32.4
Requires-Dist: whitenoise==6.9.0
